duktr/__init__.py
duktr/core.py
duktr/llm_providers.py
duktr/miner.py
duktr/prompt.py
duktr/utils.py
duktr-0.1.0.dist-info/licenses/LICENSE
duktr-0.1.0.dist-info/METADATA
duktr-0.1.0.dist-info/WHEEL
duktr-0.1.0.dist-info/top_level.txt
duktr-0.1.0.dist-info/RECORD
