Metadata-Version: 2.4
Name: duktr
Version: 0.1.0
Summary: An LLM-powered Python package for dynamic concept mining and mixed-membership clustering over text.
Author-email: Amin <amin.shoarinejad@gmail.com>
License: MIT License
Project-URL: Homepage, https://github.com/Aminsn/duktr
Classifier: Programming Language :: Python :: 3
Classifier: Operating System :: OS Independent
Requires-Python: >=3.9
License-File: LICENSE
Requires-Dist: requests>=2.0
Provides-Extra: test
Requires-Dist: pytest; extra == "test"
Requires-Dist: urllib3<2; extra == "test"
Dynamic: license-file
